blinkter/__init__.py
blinkter/board.py
blinkter/led.py
blinkter/pixel.py
blinkter/threads.py
blinkter-0.1.5.6.dist-info/LICENSE
blinkter-0.1.5.6.dist-info/METADATA
blinkter-0.1.5.6.dist-info/WHEEL
blinkter-0.1.5.6.dist-info/top_level.txt
blinkter-0.1.5.6.dist-info/RECORD
