Metadata-Version: 2.1
Name: blinkter
Version: 0.1.5.6
Summary: A high level library for interacting with the Pimoroni Blinkt.
Home-page: https://github.com/speratus/Blinkter
Author: Andrew Luchuk
Author-email: spaxumof@gmail.com
License: UNKNOWN
Platform: UNKNOWN
Classifier: Programming Language :: Python :: 3
Classifier: Programming Language :: Python :: 3.5
Classifier: Programming Language :: Python :: 3.7
Classifier: License :: OSI Approved :: MIT License
Classifier: Operating System :: POSIX :: Linux
Requires-Dist: blinkt (>=0.1.2)
